Workbook

Sheet Sheet1
A1: S.NO | B1: APP ID | C1: DISBURSEMENT DATE | D1: CASE LOCATION | E1: CASE STATE | F1: CUSTOMER NAME | G1: CUSTOMER'S FIRM NAME | H1: BANK NAME | I1: PRODUCT NAME | J1: GROUP | K1: FRESH/BT | L1: ANY SUBVENTION | M1: DISBURSE AMOUNT | N1: OTC/PDD STATUS | O1: PF TAKEN | P1: COMMISSION RATE | Q1: BANKER NAME | R1: BANKER NO. | S1: BANKER EMAIL
A2: =IF(COUNTA(B2:I2, K2:S2)>0, ROW()-1, " ") | J2: =IF(I2="", "", _xlfn.XLOOKUP(I2, Sheet2!$XEY$2:$XEY$91, Sheet2!$XEZ$2:$XEZ$91, " ", 0))
A3: =IF(COUNTA(B3:I3, K3:S3)>0, ROW()-1, " ") | J3: =IF(I3="", "", _xlfn.XLOOKUP(I3, Sheet2!$XEY$2:$XEY$91, Sheet2!$XEZ$2:$XEZ$91, " ", 0))
A4: =IF(COUNTA(B4:I4, K4:S4)>0, ROW()-1, " ") | J4: =IF(I4="", "", _xlfn.XLOOKUP(I4, Sheet2!$XEY$2:$XEY$91, Sheet2!$XEZ$2:$XEZ$91, " ", 0))
A5: =IF(COUNTA(B5:I5, K5:S5)>0, ROW()-1, " ") | J5: =IF(I5="", "", _xlfn.XLOOKUP(I5, Sheet2!$XEY$2:$XEY$91, Sheet2!$XEZ$2:$XEZ$91, " ", 0))
A6: =IF(COUNTA(B6:I6, K6:S6)>0, ROW()-1, " ") | J6: =IF(I6="", "", _xlfn.XLOOKUP(I6, Sheet2!$XEY$2:$XEY$91, Sheet2!$XEZ$2:$XEZ$91, " ", 0))
A7: =IF(COUNTA(B7:I7, K7:S7)>0, ROW()-1, " ") | J7: =IF(I7="", "", _xlfn.XLOOKUP(I7, Sheet2!$XEY$2:$XEY$91, Sheet2!$XEZ$2:$XEZ$91, " ", 0))
A8: =IF(COUNTA(B8:I8, K8:S8)>0, ROW()-1, " ") | J8: =IF(I8="", "", _xlfn.XLOOKUP(I8, Sheet2!$XEY$2:$XEY$91, Sheet2!$XEZ$2:$XEZ$91, " ", 0))
A9: =IF(COUNTA(B9:I9, K9:S9)>0, ROW()-1, " ") | J9: =IF(I9="", "", _xlfn.XLOOKUP(I9, Sheet2!$XEY$2:$XEY$91, Sheet2!$XEZ$2:$XEZ$91, " ", 0))
A10: =IF(COUNTA(B10:I10, K10:S10)>0, ROW()-1, " ") | J10: =IF(I10="", "", _xlfn.XLOOKUP(I10, Sheet2!$XEY$2:$XEY$91, Sheet2!$XEZ$2:$XEZ$91, " ", 0))
A11: =IF(COUNTA(B11:I11, K11:S11)>0, ROW()-1, " ") | J11: =IF(I11="", "", _xlfn.XLOOKUP(I11, Sheet2!$XEY$2:$XEY$91, Sheet2!$XEZ$2:$XEZ$91, " ", 0))
A12: =IF(COUNTA(B12:I12, K12:S12)>0, ROW()-1, " ") | J12: =IF(I12="", "", _xlfn.XLOOKUP(I12, Sheet2!$XEY$2:$XEY$91, Sheet2!$XEZ$2:$XEZ$91, " ", 0))
A13: =IF(COUNTA(B13:I13, K13:S13)>0, ROW()-1, " ") | J13: =IF(I13="", "", _xlfn.XLOOKUP(I13, Sheet2!$XEY$2:$XEY$91, Sheet2!$XEZ$2:$XEZ$91, " ", 0))
... A999: =IF(COUNTA(B999:I999, K999:S999)>0, ROW()-1, " ") | J999: =IF(I999="", "", _xlfn.XLOOKUP(I999, Sheet2!$XEY$2:$XEY$91, Sheet2!$XEZ$2:$XEZ$91, " ", 0))

Sheet Sheet2
XEX1: Product ID | XEY1: Product Name | XEZ1: Group | XFB1: Bank ID | XFC1: Bank Name | XFD1: Short Name
XEX2: 1 | XEY2: HL | XEZ2: Secured | XFB2: 1 | XFC2: Aadhar Housing Finance Ltd | XFD2: Aadhar
XEX3: 2 | XEY3: LAP | XEZ3: Secured | XFB3: 2 | XFC3: Aavas Financiers Ltd | XFD3: Aavas
XEX4: 3 | XEY4: HL/LAP | XEZ4: Secured | XFB4: 3 | XFC4: Aditya Birla Finance Limited | XFD4: ABFL
XEX5: 4 | XEY5: BIL | XEZ5: Unsecured | XFB5: 4 | XFC5: Aditya Birla Finance Limited Digital | XFD5: ABFL Digital Bank
XEX6: 5 | XEY6: BL | XEZ6: Unsecured | XFB6: 5 | XFC6: Aditya Birla Housing Finance Ltd | XFD6: ABHFL
XEX7: 6 | XEY7: BL OD | XEZ7: Unsecured | XFB7: 6 | XFC7: Tyger Home Finance (Adani Housing) | XFD7: Adani Housing
XEX8: 7 | XEY8: Doctor Loan | XEZ8: Unsecured | XFB8: 7 | XFC8: Agrim Housing Finance Ltd | XFD8: Agrim
XEX9: 8 | XEY9: PL | XEZ9: Unsecured | XFB9: 8 | XFC9: Agriwise Finserv Ltd | XFD9: Agriwise
XEX10: 9 | XEY10: PL OD | XEZ10: Unsecured | XFB10: 11 | XFC10: Arka Fincap Ltd | XFD10: Arka
XEX11: 10 | XEY11: STSL | XEZ11: Secured | XFB11: 12 | XFC11: Art Housing Finance Ltd | XFD11: Art Housing
XEX12: 11 | XEY12: STUL | XEZ12: Unsecured | XFB12: 13 | XFC12: Ashv Finance | XFD12: Ashv
XEX13: 12 | XEY13: Term Loan Secured | XEZ13: Secured | XFB13: 14 | XFC13: AU Small Finance Bank Ltd | XFD13: AU Bank
... XEX49: 52 | XEY49: test | XEZ49: Unsecured | XFB49: 50 | XFC49: SMFG Grihashakti Home Finance | XFD49: Grihashakti
XFB50: 51 | XFC50: HDB Financial Services | XFD50: HDB Bank
XFB51: 52 | XFC51: HDFC Bank | XFD51: HDFC
XFB52: 53 | XFC52: Hero FinCorp | XFD52: Hero
XFB53: 54 | XFC53: Hinduja Leyland Finance | XFD53: Hinduja
XFB54: 55 | XFC54: ICICI Bank | XFD54: ICICI
XFB55: 56 | XFC55: ICICI Home Finance | XFD55: ICICI HFC
XFB56: 57 | XFC56: IDBI Bank | XFD56: IDBI Bank
XFB57: 58 | XFC57: IDFC First Bank | XFD57: IDFC First Bank
XFB58: 59 | XFC58: IIFL Finance | XFD58: IIFL Bank
XFB59: 60 | XFC59: IKF Home Finance Ltd | XFD59: IKF Home Finance
XFB60: 61 | XFC60: InCred Finance | XFD60: INCRED
XFB61: 62 | XFC61: Indiabulls Home Loan | XFD61: Indiabulls
... XFB134: 136 | XFC134: Fed Bank | XFD134: Fed Bank
