Workbook

Sheet Sheet1
A1: S.NO | B1: Company Name | C1: APP ID | D1: DISBURSEMENT DATE | E1: CASE LOCATION | F1: CASE STATE | G1: CUSTOMER NAME | H1: CUSTOMER PHONE NUMBER | I1: CUSTOMER'S FIRM NAME | J1: BANK NAME | K1: PRODUCT NAME | L1: GROUP | M1: FRESH/BT | N1: ANY SUBVENTION | O1: DISBURSE AMOUNT | P1: OTC/PDD STATUS | Q1: PF TAKEN | R1: COMMISSION RATE | S1: BANKER NAME | T1: BANKER NO. | U1: BANKER EMAIL
A2: =IF(COUNTA(C2:K2, M2:U2)>0, ROW()-1, " ") | L2: =IF(K2="", "", _xlfn.XLOOKUP(K2, Sheet2!$XEY$2:$XEY$91, Sheet2!$XEZ$2:$XEZ$91, " ", 0))
L3: =IF(K3="", "", _xlfn.XLOOKUP(K3, Sheet2!$XEY$2:$XEY$91, Sheet2!$XEZ$2:$XEZ$91, " ", 0))
L4: =IF(K4="", "", _xlfn.XLOOKUP(K4, Sheet2!$XEY$2:$XEY$91, Sheet2!$XEZ$2:$XEZ$91, " ", 0))
L5: =IF(K5="", "", _xlfn.XLOOKUP(K5, Sheet2!$XEY$2:$XEY$91, Sheet2!$XEZ$2:$XEZ$91, " ", 0))
L6: =IF(K6="", "", _xlfn.XLOOKUP(K6, Sheet2!$XEY$2:$XEY$91, Sheet2!$XEZ$2:$XEZ$91, " ", 0))
L7: =IF(K7="", "", _xlfn.XLOOKUP(K7, Sheet2!$XEY$2:$XEY$91, Sheet2!$XEZ$2:$XEZ$91, " ", 0))
L8: =IF(K8="", "", _xlfn.XLOOKUP(K8, Sheet2!$XEY$2:$XEY$91, Sheet2!$XEZ$2:$XEZ$91, " ", 0))
L9: =IF(K9="", "", _xlfn.XLOOKUP(K9, Sheet2!$XEY$2:$XEY$91, Sheet2!$XEZ$2:$XEZ$91, " ", 0))
L10: =IF(K10="", "", _xlfn.XLOOKUP(K10, Sheet2!$XEY$2:$XEY$91, Sheet2!$XEZ$2:$XEZ$91, " ", 0))
L11: =IF(K11="", "", _xlfn.XLOOKUP(K11, Sheet2!$XEY$2:$XEY$91, Sheet2!$XEZ$2:$XEZ$91, " ", 0))
L12: =IF(K12="", "", _xlfn.XLOOKUP(K12, Sheet2!$XEY$2:$XEY$91, Sheet2!$XEZ$2:$XEZ$91, " ", 0))
L13: =IF(K13="", "", _xlfn.XLOOKUP(K13, Sheet2!$XEY$2:$XEY$91, Sheet2!$XEZ$2:$XEZ$91, " ", 0))
L14: =IF(K14="", "", _xlfn.XLOOKUP(K14, Sheet2!$XEY$2:$XEY$91, Sheet2!$XEZ$2:$XEZ$91, " ", 0))
... L998: =IF(K998="", "", _xlfn.XLOOKUP(K998, Sheet2!$XEY$2:$XEY$91, Sheet2!$XEZ$2:$XEZ$91, " ", 0))

Sheet Sheet2
XER1: Company | XEX1: Product ID | XEY1: Product Name | XEZ1: Group | XFB1: Bank ID | XFC1: Bank Name | XFD1: Short Name
XER2: Parker's Consulting & Ventures Pvt. Ltd. | XEX2: 1 | XEY2: HL | XEZ2: Secured | XFB2: 1 | XFC2: Aadhar Housing Finance Ltd | XFD2: Aadhar
XER3: Aadrika Informative Services Pvt. LTD | XEX3: 2 | XEY3: LAP | XEZ3: Secured | XFB3: 2 | XFC3: Aavas Financiers Ltd | XFD3: Aavas
XER4: Finance Solution | XEX4: 3 | XEY4: HL/LAP | XEZ4: Secured | XFB4: 3 | XFC4: Aditya Birla Finance Limited | XFD4: ABFL
XEX5: 4 | XEY5: BIL | XEZ5: Unsecured | XFB5: 4 | XFC5: Aditya Birla Finance Limited Digital | XFD5: ABFL Digital Bank
XEX6: 5 | XEY6: BL | XEZ6: Unsecured | XFB6: 5 | XFC6: Aditya Birla Housing Finance Ltd | XFD6: ABHFL
XEX7: 6 | XEY7: BL OD | XEZ7: Unsecured | XFB7: 6 | XFC7: Tyger Home Finance (Adani Housing) | XFD7: Adani Housing
XEX8: 7 | XEY8: Doctor Loan | XEZ8: Unsecured | XFB8: 7 | XFC8: Agrim Housing Finance Ltd | XFD8: Agrim
XEX9: 8 | XEY9: PL | XEZ9: Unsecured | XFB9: 8 | XFC9: Agriwise Finserv Ltd | XFD9: Agriwise
XEX10: 9 | XEY10: PL OD | XEZ10: Unsecured | XFB10: 11 | XFC10: Arka Fincap Ltd | XFD10: Arka
XEX11: 10 | XEY11: STSL | XEZ11: Secured | XFB11: 12 | XFC11: Art Housing Finance Ltd | XFD11: Art Housing
XEX12: 11 | XEY12: STUL | XEZ12: Unsecured | XFB12: 13 | XFC12: Ashv Finance | XFD12: Ashv
XEX13: 12 | XEY13: Term Loan Secured | XEZ13: Secured | XFB13: 14 | XFC13: AU Small Finance Bank Ltd | XFD13: AU Bank
XEX14: 13 | XEY14: Udyog | XEZ14: Unsecured | XFB14: 15 | XFC14: Axis Bank | XFD14: AXIS
XEX15: 14 | XEY15: LAP OD | XEZ15: Secured | XFB15: 16 | XFC15: Axis Finance | XFD15: Axis Finance
XEX16: 15 | XEY16: MSME - TL | XEZ16: Secured | XFB16: 17 | XFC16: Bajaj Finserv Ltd | XFD16: Bajaj
... XEX48: 51 | XEY48: BWC/OD | XEZ48: Secured | XFB48: 49 | XFC48: Godrej Capital | XFD48: GODREJ
XFB49: 50 | XFC49: SMFG Grihashakti Home Finance | XFD49: Grihashakti
XFB50: 51 | XFC50: HDB Financial Services | XFD50: HDB Bank
XFB51: 52 | XFC51: HDFC Bank | XFD51: HDFC
XFB52: 53 | XFC52: Hero FinCorp | XFD52: Hero
XFB53: 54 | XFC53: Hinduja Leyland Finance | XFD53: Hinduja
XFB54: 55 | XFC54: ICICI Bank | XFD54: ICICI
XFB55: 56 | XFC55: ICICI Home Finance | XFD55: ICICI HFC
XFB56: 57 | XFC56: IDBI Bank | XFD56: IDBI Bank
XFB57: 58 | XFC57: IDFC First Bank | XFD57: IDFC First Bank
XFB58: 59 | XFC58: IIFL Finance | XFD58: IIFL Bank
XFB59: 60 | XFC59: IKF Home Finance Ltd | XFD59: IKF Home Finance
XFB60: 61 | XFC60: InCred Finance | XFD60: INCRED
... XFB134: 136 | XFC134: Fed Bank | XFD134: Fed Bank
